{"created_at": "2026-04-18T06:26:42.594595+08:00", "train_time": 21681, "train_step": 64959, "platform": "tencent_kaiwu", "business": "competition", "user_id": 1, "team_id": 2, "project_code": "gorge_chase", "project_version": "15.0.1", "task_id": "uuid", "algorithm": "ppo", "model_file_name": "gorge_chase-ppo-64959-2026_04_18_06_26_42-15.0.1.zip", "model_file_hash": "0a1c6e1ef275be42cc14bf5be61bc6be56c54639e7af9d8136cab9c7cae4cb2d", "model_file_path": ["ckpt/model.ckpt-64959.pkl"], "signature": null}